signature_detect/cropper.py
signature_detect/extractor.py
signature_detect/judger.py
signature_detect/loader.py
signature_detection/cropper.py
signature_detection/extractor.py
signature_detection/judger.py
signature_detection/loader.py
signature_detect-0.1.4.dist-info/LICENSE
signature_detect-0.1.4.dist-info/METADATA
signature_detect-0.1.4.dist-info/WHEEL
signature_detect-0.1.4.dist-info/top_level.txt
signature_detect-0.1.4.dist-info/RECORD
