Metadata-Version: 2.1
Name: signature-detect
Version: 0.1.4
Summary: A package for the signature detection
Home-page: https://github.com/EnzoSeason/signature_detection
Author: Jijie LIU
Author-email: liujijieseason@gmail.com
License: MIT
Platform: UNKNOWN
Provides-Extra: dev
